MANIFEST.in
README.md
requirements.txt
setup.py
namedparser/__init__.py
namedparser/_actions.py
namedparser/parser.py
namedparser/structures.py
namedparser.egg-info/PKG-INFO
namedparser.egg-info/SOURCES.txt
namedparser.egg-info/dependency_links.txt
namedparser.egg-info/not-zip-safe
namedparser.egg-info/requires.txt
namedparser.egg-info/top_level.txt
namedparser/testsuite/__init__.py
namedparser/testsuite/helper.py
namedparser/testsuite/test_parser.py
namedparser/testsuite/test_suite_for_myserver.py