Metadata-Version: 1.1
Name: namedparser
Version: 0.0.3
Summary: Read name-daemon configuration files like the bind
Home-page: https://github.com/hachibeeDI/namedparser
Author: OGURA_Daiki
Author-email: 8hachibee125@gmail.com
License: MIT
Keywords: bind,named
Platform: any
Classifier: Development Status :: 4 - Beta
Classifier: License :: OSI Approved :: MIT License
Classifier: Programming Language :: Python
Classifier: Topic :: Software Development :: Libraries :: Python Modules
